{
  "mapId": 135,
  "mapName": "Precious Garden",
  "width": 128,
  "height": 256,
  "componentCount": 3,
  "areas": [
    {
      "sceneScriptId": 1,
      "tileTypeValues": [
        2
      ],
      "auxValues": [
        0,
        64,
        65
      ],
      "tileCount": 103,
      "bbox": {
        "minX": 62,
        "minY": 240,
        "maxX": 71,
        "maxY": 252
      },
      "rowRuns": [
        {
          "y": 240,
          "startX": 63,
          "endX": 70
        },
        {
          "y": 241,
          "startX": 62,
          "endX": 71
        },
        {
          "y": 242,
          "startX": 62,
          "endX": 71
        },
        {
          "y": 243,
          "startX": 62,
          "endX": 71
        },
        {
          "y": 244,
          "startX": 62,
          "endX": 71
        },
        {
          "y": 245,
          "startX": 62,
          "endX": 71
        },
        {
          "y": 246,
          "startX": 62,
          "endX": 71
        },
        {
          "y": 247,
          "startX": 62,
          "endX": 71
        },
        {
          "y": 248,
          "startX": 63,
          "endX": 71
        },
        {
          "y": 249,
          "startX": 64,
          "endX": 70
        },
        {
          "y": 250,
          "startX": 65,
          "endX": 69
        },
        {
          "y": 251,
          "startX": 66,
          "endX": 68
        },
        {
          "y": 252,
          "startX": 67,
          "endX": 67
        }
      ],
      "componentIndex": 1
    },
    {
      "sceneScriptId": 2,
      "tileTypeValues": [
        2
      ],
      "auxValues": [
        64
      ],
      "tileCount": 129,
      "bbox": {
        "minX": 0,
        "minY": 158,
        "maxX": 8,
        "maxY": 172
      },
      "rowRuns": [
        {
          "y": 158,
          "startX": 0,
          "endX": 6
        },
        {
          "y": 159,
          "startX": 0,
          "endX": 7
        },
        {
          "y": 160,
          "startX": 0,
          "endX": 8
        },
        {
          "y": 161,
          "startX": 0,
          "endX": 8
        },
        {
          "y": 162,
          "startX": 0,
          "endX": 8
        },
        {
          "y": 163,
          "startX": 0,
          "endX": 8
        },
        {
          "y": 164,
          "startX": 0,
          "endX": 8
        },
        {
          "y": 165,
          "startX": 0,
          "endX": 8
        },
        {
          "y": 166,
          "startX": 0,
          "endX": 8
        },
        {
          "y": 167,
          "startX": 0,
          "endX": 8
        },
        {
          "y": 168,
          "startX": 0,
          "endX": 8
        },
        {
          "y": 169,
          "startX": 0,
          "endX": 8
        },
        {
          "y": 170,
          "startX": 0,
          "endX": 8
        },
        {
          "y": 171,
          "startX": 0,
          "endX": 7
        },
        {
          "y": 172,
          "startX": 0,
          "endX": 6
        }
      ],
      "componentIndex": 2
    },
    {
      "sceneScriptId": 3,
      "tileTypeValues": [
        2
      ],
      "auxValues": [
        64
      ],
      "tileCount": 131,
      "bbox": {
        "minX": 60,
        "minY": 0,
        "maxX": 72,
        "maxY": 10
      },
      "rowRuns": [
        {
          "y": 0,
          "startX": 61,
          "endX": 72
        },
        {
          "y": 1,
          "startX": 61,
          "endX": 72
        },
        {
          "y": 2,
          "startX": 61,
          "endX": 72
        },
        {
          "y": 3,
          "startX": 60,
          "endX": 72
        },
        {
          "y": 4,
          "startX": 60,
          "endX": 72
        },
        {
          "y": 5,
          "startX": 60,
          "endX": 72
        },
        {
          "y": 6,
          "startX": 60,
          "endX": 72
        },
        {
          "y": 7,
          "startX": 61,
          "endX": 72
        },
        {
          "y": 8,
          "startX": 61,
          "endX": 72
        },
        {
          "y": 9,
          "startX": 61,
          "endX": 71
        },
        {
          "y": 10,
          "startX": 63,
          "endX": 70
        }
      ],
      "componentIndex": 3
    }
  ]
}